{
  "title": "Best Ever Shrimp Dip",
  "directions": [
    "In a medium bowl, mix together cream cheese and mayonnaise. Mix in onion, celery and shrimp meat. Cover bowl, and refrigerate before serving."
  ],
  "ingredients": [
    "1 (8 ounce) package cream cheese, softened",
    "1 cup mayonnaise",
    "1/4 cup chopped onion",
    "1/4 cup chopped celery",
    "1/2 pound cooked and peeled shrimp"
  ],
  "lang": "en-US",
  "tags": [],
  "source": "All Recipes",
  "sourceUrl": "http://allrecipes.com/recipe/14818/best-ever-shrimp-dip/"
}