{
  "title": "California Date Shakes",
  "directions": [
    "Blend all ingredients in a blender just until smooth with some small bits of date."
  ],
  "ingredients": [
    "3 cups premium vanilla ice cream",
    "1 cup whole milk",
    "1 cup whole pitted dates"
  ],
  "lang": "en-US",
  "tags": [
    "Milk/Cream",
    "Non-Alcoholic",
    "Blender",
    "Quick & Easy",
    "Date",
    "Summer",
    "Gourmet",
    "Drink"
  ],
  "source": "Epicurious",
  "sourceUrl": "http://www.epicurious.com/recipes/food/views/california-date-shakes-235047"
}