{
  "title": "Chipotle-Lime Salt",
  "directions": [
    "Toss 2 tablespoons flaky sea salt and 1 teaspoon chipotle chili powder on a baking sheet. Finely zest 2 limes over. Bake in a 350°F oven, stirring occasionally, until lime zest is dry, about 5 minutes. Let cool."
  ],
  "ingredients": [
    "2 tablespoons flaky sea salt",
    "1 teaspoon chipotle chili powder",
    "Zest of 2 limes"
  ],
  "lang": "en-US",
  "tags": [
    "Bake",
    "Lime"
  ],
  "source": "Epicurious",
  "sourceUrl": "http://www.epicurious.com/recipes/food/views/chipotle-lime-salt-51179410"
}