{
  "title": "Fried Cabbage",
  "directions": [
    "Cook and stir bacon, onions, and bell pepper together in a skillet over medium heat until bacon is just starting to brown, about 10 minutes. Add cabbage and cook, stirring frequently, until cabbage is tender and transparent, 20 to 30 minutes."
  ],
  "ingredients": [
    "1 pound bacon, diced",
    "2 onions, chopped",
    "1 cup diced bell pepper",
    "1 head cabbage, chopped"
  ],
  "lang": "en-US",
  "tags": [],
  "source": "All Recipes",
  "sourceUrl": "http://allrecipes.com/recipe/235987/fried-cabbage/"
}