{
  "title": "Honey-Brandy Oranges",
  "directions": [
    "Remove peel and white pith from oranges. Cut oranges between membranes and release segments into bowl.",
    "Stir remaining ingredients in small saucepan over medium-low heat just until syrup is bubbling at edges, about 6 minutes. Pour mixture over orange segments. Refrigerate until cold, about 1 hour. (Can be made 1 day ahead. Keep refrigerated.)"
  ],
  "ingredients": [
    "5 oranges",
    "1/4 cup brandy",
    "1/4 cup honey",
    "1 teaspoon grated orange peel"
  ],
  "lang": "en-US",
  "tags": [
    "Fruit",
    "Dessert",
    "Quick & Easy",
    "Orange",
    "Brandy",
    "Honey"
  ],
  "source": "Epicurious",
  "sourceUrl": "http://www.epicurious.com/recipes/food/views/honey-brandy-oranges-107171"
}