{
  "title": "Peanut Butter and Honey Sandwich",
  "directions": [
    "Stir the peanut butter, honey, and butter together in a bowl until smooth; spread on 1 of the bread slices and sandwich with the other slice."
  ],
  "ingredients": [
    "2 tablespoons peanut butter",
    "1 teaspoon honey",
    "1 teaspoon butter, softened",
    "2 slices bread"
  ],
  "lang": "en-US",
  "tags": [],
  "source": "All Recipes",
  "sourceUrl": "http://allrecipes.com/recipe/199631/peanut-butter-and-honey-sandwich/"
}