{
  "title": "Rich Cheese Pie",
  "directions": [
    "Preheat oven to 425 degrees F (220 degrees C). Spread shredded cheese in the bottom of pie crust.",
    "In a large bowl, combine eggs, cream and milk. Season with hot sauce, salt, pepper and paprika.  Pour filling over shredded cheese in the pie crust.",
    "Bake in the preheated oven for 40 to 50 minutes, or until golden brown. Cool 10 minutes before serving."
  ],
  "ingredients": [
    "1 ½ cups shredded Cheddar cheese",
    "4  eggs",
    "1 cup heavy cream",
    "1 cup milk",
    "3 drops hot sauce",
    "¼ teaspoon salt",
    "¼ teaspoon pepper",
    "¼ teaspoon paprika",
    "1 (9 inch) unbaked pie crust"
  ],
  "lang": "en-US",
  "tags": [],
  "source": "All Recipes",
  "sourceUrl": "http://allrecipes.com/recipe/23146/rich-cheese-pie/"
}