{
  "title": "Southern Style Dry Rub for Pork or Chicken",
  "directions": [
    "Whisk brown sugar, paprika, salt, black pepper, garlic powder, onion powder, and cayenne pepper together in a bowl. Store in an airtight container."
  ],
  "ingredients": [
    "1/4 cup brown sugar",
    "1/4 cup paprika",
    "1/4 cup coarse salt",
    "2 tablespoons freshly ground black pepper",
    "2 tablespoons garlic powder",
    "2 tablespoons onion powder",
    "1 tablespoon cayenne pepper"
  ],
  "lang": "en-US",
  "tags": [],
  "source": "All Recipes",
  "sourceUrl": "http://allrecipes.com/recipe/240076/southern-style-dry-rub-for-pork-or-ch/"
}