{
  "title": "Spicy Oatmeal Cookies",
  "directions": [
    "Preheat the oven to 400 degrees F (200 degrees C).",
    "In a large bowl, stir together the flour, sugar, baking soda, salt, nutmeg and cinnamon. Cut in the shortening, until the mixture appears mealy. Stir in the egg, mashed banana and oatmeal until well blended. Drop by rounded spoonfuls onto an unprepared cookie sheet.",
    "Bake for 8 to 10 minutes in the preheated oven. Remove from baking sheet to cool on wire racks."
  ],
  "ingredients": [
    "1 ½ cups all-purpose flour",
    "1 cup white sugar",
    "½ teaspoon baking soda",
    "1 teaspoon salt",
    "¼ teaspoon ground nutmeg",
    "¾ teaspoon ground cinnamon",
    "¾ cup shortening",
    "1  egg, beaten",
    "1  banana",
    "1 ¾ cups rolled oats"
  ],
  "lang": "en-US",
  "tags": [],
  "source": "All Recipes",
  "sourceUrl": "http://allrecipes.com/recipe/17233/spicy-oatmeal-cookies/"
}