{
  "title": "Tropical Rum Shake",
  "directions": [
    "In a blender, blend all ingredients until smooth but still thick and pour into 2 chilled stemmed glasses."
  ],
  "ingredients": [
    "1 pint (2 cups) softened vanilla ice cream",
    "1 ounce (2 tablespoons) light rum, or to taste",
    "1/2 ounce (1 tablespoon) crème de cacao, or to taste",
    "1 tablespoon chopped crystallized gingerroot"
  ],
  "lang": "en-US",
  "tags": [
    "Liqueur",
    "Rum",
    "Alcoholic",
    "Blender",
    "Ginger",
    "Dessert",
    "Spirit",
    "Créme de Cacao",
    "Summer",
    "Party",
    "Gourmet",
    "Drink",
    "Vegetarian",
    "Pescatarian",
    "Wheat/Gluten-Free",
    "Peanut Free",
    "Tree Nut Free",
    "Soy Free",
    "Kosher"
  ],
  "source": "Epicurious",
  "sourceUrl": "http://www.epicurious.com/recipes/food/views/tropical-rum-shake-200655"
}